[
    {
        "key": "dbln",
        "value": "%7B%22100033685782498%22%3A%22jaJscZRl%22%2C%2261559899700574%22%3A%22URbQLq15%22%2C%22100094264414225%22%3A%22Wcb0FrbK%22%2C%22100024307230123%22%3A%224JZ0KT4J%22%2C%22100000163058350%22%3A%22mGfIm0Cg%22%7D",
        "domain": "facebook.com",
        "path": "/login/device-based/",
        "hostOnly": false,
        "creation": "2025-08-14T08:55:29.300Z",
        "lastAccessed": "2025-08-14T08:55:29.300Z"
    },
    {
        "key": "sb",
        "value": "afQaaINdDe3UTqaxCvYJiOXx",
        "domain": "facebook.com",
        "path": "/",
        "hostOnly": false,
        "creation": "2025-08-14T08:55:29.300Z",
        "lastAccessed": "2025-08-14T08:55:29.300Z"
    },
    {
        "key": "vpd",
        "value": "v1%3B980x501x2.026643991470337",
        "domain": "facebook.com",
        "path": "/",
        "hostOnly": false,
        "creation": "2025-08-14T08:55:29.300Z",
        "lastAccessed": "2025-08-14T08:55:29.300Z"
    },
    {
        "key": "pas",
        "value": "100000163058350%3ABDxbK8TBkJ",
        "domain": "facebook.com",
        "path": "/",
        "hostOnly": false,
        "creation": "2025-08-14T08:55:29.300Z",
        "lastAccessed": "2025-08-14T08:55:29.300Z"
    },
    {
        "key": "dpr",
        "value": "2.228187322616577",
        "domain": "facebook.com",
        "path": "/",
        "hostOnly": false,
        "creation": "2025-08-14T08:55:29.300Z",
        "lastAccessed": "2025-08-14T08:55:29.300Z"
    },
    {
        "key": "datr",
        "value": "7ZWdaKx1FTNzOfea_66v7AeY",
        "domain": "facebook.com",
        "path": "/",
        "hostOnly": false,
        "creation": "2025-08-14T08:55:29.300Z",
        "lastAccessed": "2025-08-14T08:55:29.300Z"
    },
    {
        "key": "locale",
        "value": "en_GB",
        "domain": "facebook.com",
        "path": "/",
        "hostOnly": false,
        "creation": "2025-08-14T08:55:29.300Z",
        "lastAccessed": "2025-08-14T08:55:29.300Z"
    },
    {
        "key": "ps_l",
        "value": "1",
        "domain": "facebook.com",
        "path": "/",
        "hostOnly": false,
        "creation": "2025-08-14T08:55:29.300Z",
        "lastAccessed": "2025-08-14T08:55:29.300Z"
    },
    {
        "key": "ps_n",
        "value": "1",
        "domain": "facebook.com",
        "path": "/",
        "hostOnly": false,
        "creation": "2025-08-14T08:55:29.300Z",
        "lastAccessed": "2025-08-14T08:55:29.300Z"
    },
    {
        "key": "c_user",
        "value": "100000163058350",
        "domain": "facebook.com",
        "path": "/",
        "hostOnly": false,
        "creation": "2025-08-14T08:55:29.300Z",
        "lastAccessed": "2025-08-14T08:55:29.300Z"
    },
    {
        "key": "xs",
        "value": "1%3ADz7bA9TAB-hgkQ%3A2%3A1755161668%3A-1%3A-1",
        "domain": "facebook.com",
        "path": "/",
        "hostOnly": false,
        "creation": "2025-08-14T08:55:29.300Z",
        "lastAccessed": "2025-08-14T08:55:29.300Z"
    },
    {
        "key": "wd",
        "value": "948x1855",
        "domain": "facebook.com",
        "path": "/",
        "hostOnly": false,
        "creation": "2025-08-14T08:55:29.300Z",
        "lastAccessed": "2025-08-14T08:55:29.300Z"
    },
    {
        "key": "fbl_st",
        "value": "100621356%3BT%3A29252695",
        "domain": "facebook.com",
        "path": "/",
        "hostOnly": false,
        "creation": "2025-08-14T08:55:29.300Z",
        "lastAccessed": "2025-08-14T08:55:29.300Z"
    },
    {
        "key": "wl_cbv",
        "value": "v2%3Bclient_version%3A2893%3Btimestamp%3A1755161709",
        "domain": "facebook.com",
        "path": "/",
        "hostOnly": false,
        "creation": "2025-08-14T08:55:29.300Z",
        "lastAccessed": "2025-08-14T08:55:29.300Z"
    },
    {
        "key": "fr",
        "value": "1Ym7n6JFkaPnG0PVY.AWfQ1Ct9A_Ccvcjq5h04fQDzAq5FL3nkWqYwWEUA-HCB5fEdkfw.BonZv4..AAA.0.0.BonaR3.AWcnKmStgVxN3MuKlY90ybRbm4g",
        "domain": "facebook.com",
        "path": "/",
        "hostOnly": false,
        "creation": "2025-08-14T08:55:29.300Z",
        "lastAccessed": "2025-08-14T08:55:29.300Z"
    }
        ]
